algorithmselector/__init__.py
algorithmselector/ml.py
algorithmselector/plots.py
algorithmselector_ML-1.0.0.dist-info/LICENSE
algorithmselector_ML-1.0.0.dist-info/METADATA
algorithmselector_ML-1.0.0.dist-info/WHEEL
algorithmselector_ML-1.0.0.dist-info/top_level.txt
algorithmselector_ML-1.0.0.dist-info/RECORD
