Metadata-Version: 2.1
Name: algorithmselector-ML
Version: 1.0.0
Summary: Algorithm selection library using ML and based on the scikit-learn library.
Home-page: https://github.com/mariacaseiro/algorithmselector-ML
Author: María Caseiro
Author-email: mariacaseiro24@gmail.com
License: GPL-3.0
Classifier: Programming Language :: Python :: 3
Classifier: Operating System :: OS Independent
License-File: LICENSE
